Workbook

Sheet CAPEX & OPEX
A1: Luvia Costs
A4: CAPEX Item | B4: Description | C4: One-time Cost | E4: OPEX Item | F4: Monthly Cost | G4: Annual Cost
A5: Product Development | B5: Diaper design, samples, material testing | C5: 800000 | E5: Designers | F5: 20000 | G5: =F5*12 -> 240000
A6: Tooling | B6: Prototype tooling and fit trials | C6: 700000 | E6: Operations | F6: 50000 | G6: =F6*12 -> 600000
A7: Dermatology Testing | B7: Baby-skin safety testing | C7: 300000 | E7: Marketing Team | F7: 25000 | G7: =F7*12 -> 300000
A8: Packaging Design | B8: Brand and pack design | C8: 200000 | E8: Customer Support | F8: 30000 | G8: =F8*12 -> 360000
A9: Website | B9: D2C store and subscription setup | C9: 200000 | E9: Meta / Instagram Ads | F9: 20000 | G9: =F9*12 -> 240000
A10: Branding | B10: Product and lifestyle shoot | C10: 100000 | E10: Google Ads | F10: 20000 | G10: =F10*12 -> 240000
A11: Legal & Certification | B11: Trademark, compliance, documents | C11: 500000 | E11: Influencers | F11: 40000 | G11: =F11*12 -> 480000
A12: Initial Inventory | B12: First production batch | C12: 2500000 | E12: Content Creation | F12: 25000 | G12: =F12*12 -> 300000
A13: Launch Setup | B13: Warehouse setup and launch materials | C13: 200000 | E13: Developers | F13: 30000 | G13: =F13*12 -> 360000
B14: Total CAPEX | C14: =SUM(C5:C13) -> 5500000 | E14: Accounting & Legal | F14: 5000 | G14: =F14*12 -> 60000
E15: Warehouse | F15: 100000 | G15: =F15*12 -> 1200000
E16: Shipping Support | F16: 50000 | G16: =F16*12 -> 600000
E17: Total OPEX | F17: =SUM(F5:F16) -> 415000 | G17: =SUM(G5:G16) -> 4980000

Sheet Revenue Streams
A1: Luvia Revenue Streams
A4: Revenue Source | B4: Description | C4: Customers / Orders / Brands | D4: Avg Revenue / Order | E4: Monthly Revenue | F4: Share
A5: Diaper packs | B5: Individual pack purchases | C5: 500 | D5: 2280 | E5: =C5*D5 -> 1140000 | F5: =E5/$E$13 -> 0.23651452
A6: Monthly subscriptions | B6: Recurring diaper bundle | C6: 350 | D6: 5000 | E6: =C6*D6 -> 1750000 | F6: =E6/$E$13 -> 0.36307054
A7: Amazon | B7: Marketplace orders | C7: 200 | D7: 2100 | E7: =C7*D7 -> 420000 | F7: =E7/$E$13 -> 0.087136929
A8: D2C website | B8: Direct online orders | C8: 200 | D8: 2300 | E8: =C8*D8 -> 460000 | F8: =E8/$E$13 -> 0.095435685
A9: Pharmacies | B9: Retail pharmacy orders | C9: 200 | D9: 2000 | E9: =C9*D9 -> 400000 | F9: =E9/$E$13 -> 0.082987552
A10: Baby stores | B10: Specialty baby retail | C10: 200 | D10: 2000 | E10: =C10*D10 -> 400000 | F10: =E10/$E$13 -> 0.082987552
A11: Sponsorships | B11: Brands Coupon partnerships | C11: 5 | D11: 50000 | E11: =C11*D11 -> 250000 | F11: =E11/$E$13 -> 0.05186722
A12: Partnerships | B12: Brand Products Club Partnerships | C12: 5 | D12: 50000 | E12: =C12*D12 -> 250000 | F12: =E12/$E$13 -> 0.05186722
D13: Total Monthly Revenue | E13: =SUM(E4:E11) -> 4820000

Sheet Income Statement
A1: Simple Income Statement
A4: Line Item | B4: Monthly | C4: Annual | D4: Notes | F4: Metric | G4: Value | H4: Comment
A5: Revenue | B5: ='Revenue Streams'!E13 -> 4820000 | C5: =B5*12 -> 57840000 | D5: From Revenue Streams | F5: Monthly Revenue | G5: =B5 -> 4820000 | H5: Top-line run rate
A6: COGS | B6: =B5*52% -> 2506400 | C6: =C5*52% -> 30076800 | D6: Assume 58% of revenue for premium diaper business | F6: Gross Margin | G6: =B8 -> 0.48 | H6: Before OPEX
A7: Gross Profit | B7: =B5-B6 -> 2313600 | C7: =C5-C6 -> 27763200 | D7: Revenue minus COGS | F7: Monthly EBITDA | G7: =B10 -> 1898600 | H7: Operating profitability
A8: Gross Margin % | B8: =B7/B5 -> 0.48 | C8: =B8 -> 0.48 | D8: Gross profit divided by revenue | F8: Annual Net Income | G8: =C13 -> 15712400 | H8: Final income
A9: OPEX | B9: ='CAPEX & OPEX'!F17 -> 415000 | C9: ='CAPEX & OPEX'!G17 -> 4980000 | D9: From CAPEX & OPEX sheet
A10: EBITDA | B10: =B7-B9 -> 1898600 | C10: =C7-C9 -> 22783200 | D10: Gross profit minus OPEX
A11: Depreciation | B11: ='CAPEX & OPEX'!C14/36 -> 152777.78 | C11: ='CAPEX & OPEX'!C14/3 -> 1833333.3 | D11: Simple CAPEX depreciation over 3 years | F11: Line | G11: Monthly
A12: Tax | B12: =IF(B10-B11>0,(B10-B11)*25%,0) -> 436455.56 | C12: =IF(C10-C11>0,(C10-C11)*25%,0) -> 5237466.7 | D12: 25% tax only when profit is positive | F12: Revenue | G12: =B5 -> 4820000
A13: Final Net Income | B13: =B10-B11-B12 -> 1309366.7 | C13: =C10-C11-C12 -> 15712400 | D13: Profit after depreciation and tax | F13: Gross Profit | G13: =B7 -> 2313600
A14: Opening CAPEX | B14: ='CAPEX & OPEX'!C14 -> 5500000 | C14: =B14 -> 5500000 | D14: One-time startup investment required | F14: EBITDA | G14: =B10 -> 1898600
A15: Cash Needed Before Profit | B15: =B14+IF(C13<0,-C13,0) -> 5500000 | C15: =B15 -> 5500000 | D15: CAPEX plus annual loss if negative
